mypackage_gyy/__init__.py
mypackage_gyy/_main_.py
mypackage_gyy/decorator.py
mypackage_gyy/descriptor.py
mypackage_gyy/generator.py
mypackage_gyy/iterator.py
mypackage_gyy-0.1.dist-info/METADATA
mypackage_gyy-0.1.dist-info/WHEEL
mypackage_gyy-0.1.dist-info/top_level.txt
mypackage_gyy-0.1.dist-info/RECORD
